pretix_posthog/__init__.py
pretix_posthog/apps.py
pretix_posthog/signals.py
pretix_posthog/urls.py
pretix_posthog/views.py
pretix_posthog/locale/de/LC_MESSAGES/django.mo
pretix_posthog/locale/de/LC_MESSAGES/django.po
pretix_posthog/locale/de_Informal/.gitkeep
pretix_posthog/locale/de_Informal/LC_MESSAGES/django.mo
pretix_posthog/locale/de_Informal/LC_MESSAGES/django.po
pretix_posthog/static/pretix_posthog/.gitkeep
pretix_posthog/templates/pretix_posthog/.gitkeep
pretix_posthog/templates/pretix_posthog/settings.html
pretix_posthog-1.1.2.dist-info/LICENSE
pretix_posthog-1.1.2.dist-info/METADATA
pretix_posthog-1.1.2.dist-info/WHEEL
pretix_posthog-1.1.2.dist-info/entry_points.txt
pretix_posthog-1.1.2.dist-info/top_level.txt
pretix_posthog-1.1.2.dist-info/RECORD
