Metadata-Version: 2.1
Name: pretix-posthog
Version: 1.1.2
Summary: PostHog Integration for Pretix
Author-email: Daniel Malik <daniel@binarycollective.de>
Maintainer-email: Daniel Malik <daniel@binarycollective.de>
License: Apache
Project-URL: homepage, https://github.com/fronbasal/pretix-posthog
Project-URL: repository, https://github.com/fronbasal/pretix-posthog
Keywords: pretix
License-File: LICENSE
Requires-Dist: posthog >=3.5
